khamsat/__init__.py
khamsat/client.py
khamsat/http.py
khamsat_api-0.0.1.dist-info/LICENSE
khamsat_api-0.0.1.dist-info/METADATA
khamsat_api-0.0.1.dist-info/WHEEL
khamsat_api-0.0.1.dist-info/top_level.txt
khamsat_api-0.0.1.dist-info/RECORD
