Metadata-Version: 2.1
Name: khamsat-api
Version: 0.0.1
Summary: Khamsat private API for Python
Home-page: https://github.com/deounix/khamsat_api
Author: Mohammad Almoghrabi
Author-email: deounix@gmail.com
License: MIT
Platform: UNKNOWN
Requires-Dist: requests
Requires-Dist: random-useragent
